{
  "schema_version": 2,
  "run_id": "ee978f54ea8645808dc1caa015190067",
  "captured_at": "2026-05-24T21:57:04.982949+00:00",
  "status": "completed",
  "servidor": {
    "nome": "LEANDRO COLOMBI RESENDO",
    "identificador": "1687072",
    "texto_visivel": "PONTO DIÁRIO DO SERVIDOR:"
  },
  "periodo_referencia": "Maio/2025",
  "mensagens": [],
  "resumo": {
    "carga_horaria_contratada": "168:00",
    "carga_horaria_esperada_mes": "168:00",
    "total_horas_registradas": "116:25",
    "total_horas_justificadas": "53:04",
    "total_horas_homologadas": "165:02",
    "saldo_mes_anterior_compensacao": "00:00",
    "total_horas_mes_anterior_compensadas": "00:00",
    "debito_mes_anterior_nao_compensado": "00:00",
    "debito_mes_atual_nao_autorizado": "-02:50",
    "outros_debitos_nao_compensados_vencidos": "-24:00",
    "totalizacao_debito_nao_compensavel": "-26:50",
    "total_horas_pendentes_compensacao": "-24:08",
    "saldo_horas_mes": "-00:08",
    "saldo_horas_mes_compensar_proximo": "-00:08",
    "credito_horas_disponivel_mes": "00:00",
    "credito_em_horas": "00:00"
  },
  "registros": [
    {
      "data": "2025-05-01",
      "dia_semana": "Quinta",
      "marcacoes": [],
      "ocorrencias": [],
      "observacoes": [],
      "situacao": null,
      "textos_visiveis": [],
      "hr": null,
      "hc": null,
      "he": null,
      "ha": null,
      "hh": null,
      "credito": "00:00",
      "debito": null,
      "saldo_no_mes": null,
      "credito_acumulado": "00:00",
      "dnc": "00:00"
    },
    {
      "data": "2025-05-02",
      "dia_semana": null,
      "marcacoes": [],
      "ocorrencias": [],
      "observacoes": [],
      "situacao": null,
      "textos_visiveis": [],
      "hr": null,
      "hc": null,
      "he": null,
      "ha": "02/05/2025",
      "hh": null,
      "credito": null,
      "debito": null,
      "saldo_no_mes": null,
      "credito_acumulado": null,
      "dnc": null
    },
    {
      "data": "2025-05-03",
      "dia_semana": "Sábado",
      "marcacoes": [],
      "ocorrencias": [],
      "observacoes": [],
      "situacao": null,
      "textos_visiveis": [],
      "hr": null,
      "hc": null,
      "he": null,
      "ha": null,
      "hh": null,
      "credito": "00:00",
      "debito": null,
      "saldo_no_mes": null,
      "credito_acumulado": "-08:00",
      "dnc": "00:00"
    },
    {
      "data": "2025-05-04",
      "dia_semana": "Domingo",
      "marcacoes": [],
      "ocorrencias": [],
      "observacoes": [],
      "situacao": null,
      "textos_visiveis": [],
      "hr": null,
      "hc": null,
      "he": null,
      "ha": null,
      "hh": null,
      "credito": "00:00",
      "debito": null,
      "saldo_no_mes": null,
      "credito_acumulado": "-08:00",
      "dnc": "00:00"
    },
    {
      "data": "2025-05-05",
      "dia_semana": "Segunda",
      "marcacoes": [
        "08:06",
        "19:27",
        "08:06"
      ],
      "ocorrencias": [],
      "observacoes": [],
      "situacao": null,
      "textos_visiveis": [],
      "hr": "11:21",
      "hc": "11:21",
      "he": null,
      "ha": "03:21",
      "hh": "02:00",
      "credito": "10:00",
      "debito": "02:00",
      "saldo_no_mes": null,
      "credito_acumulado": "-06:00",
      "dnc": "00:00"
    },
    {
      "data": "2025-05-06",
      "dia_semana": "Terça",
      "marcacoes": [
        "07:51",
        "17:53",
        "07:51"
      ],
      "ocorrencias": [],
      "observacoes": [],
      "situacao": null,
      "textos_visiveis": [],
      "hr": "10:02",
      "hc": "10:02",
      "he": null,
      "ha": "02:02",
      "hh": "02:00",
      "credito": "10:00",
      "debito": "02:00",
      "saldo_no_mes": null,
      "credito_acumulado": "-04:00",
      "dnc": "00:00"
    },
    {
      "data": "2025-05-07",
      "dia_semana": null,
      "marcacoes": [],
      "ocorrencias": [
        "REGISTRO DO PIT - DOCENTE (07/05/2025)"
      ],
      "observacoes": [],
      "situacao": null,
      "textos_visiveis": [],
      "hr": "16:36",
      "hc": "05:24",
      "he": "08:00",
      "ha": null,
      "hh": null,
      "credito": null,
      "debito": "08:00",
      "saldo_no_mes": null,
      "credito_acumulado": null,
      "dnc": "-04:00"
    },
    {
      "data": "2025-05-08",
      "dia_semana": null,
      "marcacoes": [],
      "ocorrencias": [],
      "observacoes": [],
      "situacao": null,
      "textos_visiveis": [],
      "hr": null,
      "hc": null,
      "he": null,
      "ha": "08/05/2025",
      "hh": null,
      "credito": null,
      "debito": null,
      "saldo_no_mes": null,
      "credito_acumulado": null,
      "dnc": null
    },
    {
      "data": "2025-05-09",
      "dia_semana": "Sexta",
      "marcacoes": [
        "09:20",
        "18:30",
        "09:20"
      ],
      "ocorrencias": [],
      "observacoes": [],
      "situacao": null,
      "textos_visiveis": [],
      "hr": "09:10",
      "hc": "09:10",
      "he": null,
      "ha": "01:10",
      "hh": "01:10",
      "credito": "09:10",
      "debito": "01:10",
      "saldo_no_mes": null,
      "credito_acumulado": "-08:00",
      "dnc": "00:00"
    },
    {
      "data": "2025-05-10",
      "dia_semana": "Sábado",
      "marcacoes": [],
      "ocorrencias": [],
      "observacoes": [],
      "situacao": null,
      "textos_visiveis": [],
      "hr": null,
      "hc": null,
      "he": null,
      "ha": null,
      "hh": null,
      "credito": "00:00",
      "debito": null,
      "saldo_no_mes": null,
      "credito_acumulado": "-08:00",
      "dnc": "00:00"
    },
    {
      "data": "2025-05-11",
      "dia_semana": "Domingo",
      "marcacoes": [],
      "ocorrencias": [],
      "observacoes": [],
      "situacao": null,
      "textos_visiveis": [],
      "hr": null,
      "hc": null,
      "he": null,
      "ha": null,
      "hh": null,
      "credito": "00:00",
      "debito": null,
      "saldo_no_mes": null,
      "credito_acumulado": "-08:00",
      "dnc": "00:00"
    },
    {
      "data": "2025-05-12",
      "dia_semana": null,
      "marcacoes": [],
      "ocorrencias": [
        "REGISTRO DO PIT - DOCENTE (12/05/2025)"
      ],
      "observacoes": [],
      "situacao": null,
      "textos_visiveis": [],
      "hr": null,
      "hc": null,
      "he": "08:00",
      "ha": null,
      "hh": null,
      "credito": null,
      "debito": "08:00",
      "saldo_no_mes": null,
      "credito_acumulado": null,
      "dnc": "-08:00"
    },
    {
      "data": "2025-05-13",
      "dia_semana": "Terça",
      "marcacoes": [
        "08:19",
        "19:42",
        "08:19"
      ],
      "ocorrencias": [],
      "observacoes": [],
      "situacao": null,
      "textos_visiveis": [],
      "hr": "11:23",
      "hc": "11:23",
      "he": null,
      "ha": "03:23",
      "hh": "02:00",
      "credito": "10:00",
      "debito": "02:00",
      "saldo_no_mes": null,
      "credito_acumulado": "-06:00",
      "dnc": "00:00"
    },
    {
      "data": "2025-05-14",
      "dia_semana": null,
      "marcacoes": [],
      "ocorrencias": [
        "REGISTRO DO PIT - DOCENTE (14/05/2025)"
      ],
      "observacoes": [],
      "situacao": null,
      "textos_visiveis": [],
      "hr": null,
      "hc": null,
      "he": "Ocorrência:",
      "ha": "14/05/2025",
      "hh": "18:41",
      "credito": null,
      "debito": "08:00",
      "saldo_no_mes": null,
      "credito_acumulado": null,
      "dnc": null
    },
    {
      "data": "2025-05-15",
      "dia_semana": null,
      "marcacoes": [],
      "ocorrencias": [
        "REGISTRO DO PIT - DOCENTE (15/05/2025)"
      ],
      "observacoes": [],
      "situacao": null,
      "textos_visiveis": [],
      "hr": "09:31",
      "hc": "07:11",
      "he": "08:00",
      "ha": null,
      "hh": null,
      "credito": null,
      "debito": "08:00",
      "saldo_no_mes": null,
      "credito_acumulado": null,
      "dnc": "-06:00"
    },
    {
      "data": "2025-05-16",
      "dia_semana": "Sexta",
      "marcacoes": [
        "07:38",
        "19:16",
        "07:38"
      ],
      "ocorrencias": [],
      "observacoes": [],
      "situacao": null,
      "textos_visiveis": [],
      "hr": "11:38",
      "hc": "11:38",
      "he": null,
      "ha": "03:38",
      "hh": "02:00",
      "credito": "10:00",
      "debito": "02:00",
      "saldo_no_mes": null,
      "credito_acumulado": "-04:00",
      "dnc": "00:00"
    },
    {
      "data": "2025-05-17",
      "dia_semana": "Sábado",
      "marcacoes": [],
      "ocorrencias": [],
      "observacoes": [],
      "situacao": null,
      "textos_visiveis": [],
      "hr": null,
      "hc": null,
      "he": null,
      "ha": null,
      "hh": null,
      "credito": "00:00",
      "debito": null,
      "saldo_no_mes": null,
      "credito_acumulado": "-04:00",
      "dnc": "00:00"
    },
    {
      "data": "2025-05-18",
      "dia_semana": "Domingo",
      "marcacoes": [],
      "ocorrencias": [],
      "observacoes": [],
      "situacao": null,
      "textos_visiveis": [],
      "hr": null,
      "hc": null,
      "he": null,
      "ha": null,
      "hh": null,
      "credito": "00:00",
      "debito": null,
      "saldo_no_mes": null,
      "credito_acumulado": "-04:00",
      "dnc": "00:00"
    },
    {
      "data": "2025-05-19",
      "dia_semana": null,
      "marcacoes": [],
      "ocorrencias": [
        "REGISTRO DO PIT - DOCENTE (19/05/2025)"
      ],
      "observacoes": [],
      "situacao": null,
      "textos_visiveis": [],
      "hr": null,
      "hc": null,
      "he": "08:00",
      "ha": null,
      "hh": null,
      "credito": null,
      "debito": "08:00",
      "saldo_no_mes": null,
      "credito_acumulado": null,
      "dnc": "-04:00"
    },
    {
      "data": "2025-05-20",
      "dia_semana": "Terça",
      "marcacoes": [
        "09:03",
        "19:21",
        "09:03"
      ],
      "ocorrencias": [],
      "observacoes": [],
      "situacao": null,
      "textos_visiveis": [],
      "hr": "10:18",
      "hc": "10:18",
      "he": null,
      "ha": "02:18",
      "hh": "02:00",
      "credito": "10:00",
      "debito": "02:00",
      "saldo_no_mes": null,
      "credito_acumulado": "-02:00",
      "dnc": "00:00"
    },
    {
      "data": "2025-05-21",
      "dia_semana": null,
      "marcacoes": [],
      "ocorrencias": [
        "REGISTRO DO PIT - DOCENTE (21/05/2025)"
      ],
      "observacoes": [],
      "situacao": null,
      "textos_visiveis": [],
      "hr": null,
      "hc": null,
      "he": "Ocorrência:",
      "ha": "21/05/2025",
      "hh": "16:54",
      "credito": null,
      "debito": "08:00",
      "saldo_no_mes": null,
      "credito_acumulado": null,
      "dnc": null
    },
    {
      "data": "2025-05-22",
      "dia_semana": null,
      "marcacoes": [],
      "ocorrencias": [
        "ABONO DE HORAS (22/05/2025)"
      ],
      "observacoes": [],
      "situacao": null,
      "textos_visiveis": [],
      "hr": null,
      "hc": null,
      "he": "Ocorrência:",
      "ha": "22/05/2025",
      "hh": "08:12",
      "credito": null,
      "debito": "08:00",
      "saldo_no_mes": null,
      "credito_acumulado": null,
      "dnc": null
    },
    {
      "data": "2025-05-23",
      "dia_semana": "Sexta",
      "marcacoes": [
        "07:30",
        "17:22",
        "07:30"
      ],
      "ocorrencias": [],
      "observacoes": [],
      "situacao": null,
      "textos_visiveis": [],
      "hr": "09:52",
      "hc": "09:52",
      "he": null,
      "ha": "01:52",
      "hh": "01:52",
      "credito": "09:52",
      "debito": "01:52",
      "saldo_no_mes": null,
      "credito_acumulado": "-00:08",
      "dnc": "00:00"
    },
    {
      "data": "2025-05-24",
      "dia_semana": "Sábado",
      "marcacoes": [],
      "ocorrencias": [],
      "observacoes": [],
      "situacao": null,
      "textos_visiveis": [],
      "hr": null,
      "hc": null,
      "he": null,
      "ha": null,
      "hh": null,
      "credito": "00:00",
      "debito": null,
      "saldo_no_mes": null,
      "credito_acumulado": "-00:08",
      "dnc": "00:00"
    },
    {
      "data": "2025-05-25",
      "dia_semana": "Domingo",
      "marcacoes": [],
      "ocorrencias": [],
      "observacoes": [],
      "situacao": null,
      "textos_visiveis": [],
      "hr": null,
      "hc": null,
      "he": null,
      "ha": null,
      "hh": null,
      "credito": "00:00",
      "debito": null,
      "saldo_no_mes": null,
      "credito_acumulado": "-00:08",
      "dnc": "00:00"
    },
    {
      "data": "2025-05-26",
      "dia_semana": null,
      "marcacoes": [],
      "ocorrencias": [
        "REGISTRO DO PIT - DOCENTE (26/05/2025)"
      ],
      "observacoes": [],
      "situacao": null,
      "textos_visiveis": [],
      "hr": "13:19",
      "hc": "06:34",
      "he": "08:00",
      "ha": null,
      "hh": null,
      "credito": null,
      "debito": "08:00",
      "saldo_no_mes": null,
      "credito_acumulado": null,
      "dnc": "-00:08"
    },
    {
      "data": "2025-05-27",
      "dia_semana": "Terça",
      "marcacoes": [
        "09:19",
        "17:04",
        "09:19"
      ],
      "ocorrencias": [],
      "observacoes": [],
      "situacao": null,
      "textos_visiveis": [],
      "hr": "07:45",
      "hc": "08:00",
      "he": null,
      "ha": null,
      "hh": null,
      "credito": "08:00",
      "debito": null,
      "saldo_no_mes": null,
      "credito_acumulado": "-00:08",
      "dnc": "00:00"
    },
    {
      "data": "2025-05-28",
      "dia_semana": null,
      "marcacoes": [],
      "ocorrencias": [
        "REGISTRO DO PIT - DOCENTE (28/05/2025)"
      ],
      "observacoes": [],
      "situacao": null,
      "textos_visiveis": [],
      "hr": "13:36",
      "hc": "07:26",
      "he": "08:00",
      "ha": null,
      "hh": null,
      "credito": null,
      "debito": "08:00",
      "saldo_no_mes": null,
      "credito_acumulado": null,
      "dnc": "-00:08"
    },
    {
      "data": "2025-05-29",
      "dia_semana": null,
      "marcacoes": [],
      "ocorrencias": [
        "REGISTRO DO PIT - DOCENTE (29/05/2025)"
      ],
      "observacoes": [],
      "situacao": null,
      "textos_visiveis": [],
      "hr": "13:20",
      "hc": "03:49",
      "he": "08:00",
      "ha": null,
      "hh": null,
      "credito": null,
      "debito": "08:00",
      "saldo_no_mes": null,
      "credito_acumulado": null,
      "dnc": "-00:08"
    },
    {
      "data": "2025-05-30",
      "dia_semana": null,
      "marcacoes": [],
      "ocorrencias": [
        "REGISTRO DO PIT - DOCENTE (30/05/2025)"
      ],
      "observacoes": [],
      "situacao": null,
      "textos_visiveis": [],
      "hr": "07:27",
      "hc": "04:32",
      "he": "08:00",
      "ha": null,
      "hh": null,
      "credito": null,
      "debito": "08:00",
      "saldo_no_mes": null,
      "credito_acumulado": null,
      "dnc": "-00:08"
    },
    {
      "data": "2025-05-31",
      "dia_semana": "Sábado",
      "marcacoes": [],
      "ocorrencias": [],
      "observacoes": [],
      "situacao": null,
      "textos_visiveis": [],
      "hr": null,
      "hc": null,
      "he": null,
      "ha": null,
      "hh": null,
      "credito": "00:00",
      "debito": null,
      "saldo_no_mes": null,
      "credito_acumulado": "-00:08",
      "dnc": "00:00"
    }
  ],
  "fonte": {
    "tipo": "sigrh-espelho-ponto-visivel",
    "pagina": "/sigrh/frequencia/ponto_eletronico/consulta/consulta_ponto_eletronico.jsf",
    "rotulos_visiveis": [
      "Espelho de Ponto"
    ]
  }
}